README.rst
setup.py
netutils_linux.egg-info/PKG-INFO
netutils_linux.egg-info/SOURCES.txt
netutils_linux.egg-info/dependency_links.txt
netutils_linux.egg-info/requires.txt
netutils_linux.egg-info/top_level.txt
netutils_linux_hardware/__init__.py
netutils_linux_hardware/cpu.py
netutils_linux_hardware/disk.py
netutils_linux_hardware/folding.py
netutils_linux_hardware/grade.py
netutils_linux_hardware/interrupts.py
netutils_linux_hardware/memory.py
netutils_linux_hardware/net.py
netutils_linux_hardware/parser.py
netutils_linux_hardware/rate_math.py
netutils_linux_hardware/server.py
netutils_linux_hardware/subsystem.py
netutils_linux_hardware/system.py
netutils_linux_hardware/test_grade.py
netutils_linux_hardware/test_parsers.py
netutils_linux_hardware/yaml_tools.py
netutils_linux_monitoring/__init__.py
netutils_linux_monitoring/base_top.py
netutils_linux_monitoring/colors.py
netutils_linux_monitoring/irqtop.py
netutils_linux_monitoring/layout.py
netutils_linux_monitoring/link_rate.py
netutils_linux_monitoring/network_top.py
netutils_linux_monitoring/pci.py
netutils_linux_monitoring/snmptop.py
netutils_linux_monitoring/softirqs.py
netutils_linux_monitoring/softnet_stat.py
netutils_linux_monitoring/test_softirqs.py
netutils_linux_monitoring/test_softnet_stat.py
netutils_linux_monitoring/topology.py
netutils_linux_tuning/__init__.py
netutils_linux_tuning/auto_softirq_tune.py
netutils_linux_tuning/base_tune.py
netutils_linux_tuning/rss_ladder.py
netutils_linux_tuning/rx_buffers.py
netutils_linux_tuning/test_autorps.py
netutils_linux_tuning/test_rss_ladder.py
netutils_linux_tuning/test_rx_buffers.py
utils/autorps
utils/autotune-reductor
utils/autoxps
utils/detect_virt.py
utils/irqtop
utils/link-rate
utils/maskify
utils/maximize-cpu-freq
utils/netdev-model-list
utils/netdev-pci-speed
utils/network-top
utils/pcap-tcp-stream
utils/rss-ladder
utils/rx-buffers-increase
utils/server-info
utils/server-info-collect
utils/snmptop
utils/softirq-top
utils/softnet-stat-top
utils/subnet2iplist