Metadata-Version: 1.1
Name: netutils-linux
Version: 2.7.11
Summary: Bunch of utils to simplify linux network troubleshooting and performance tuning.
Home-page: https://github.com/strizhechenko/netutils-linux
Author: Oleg Strizhechenko
Author-email: oleg.strizhechenko@gmail.com
License: MIT
Keywords: linux network performanse utils troubleshooting irq interrupts softirqs proc
Platform: UNKNOWN
Classifier: Development Status :: 3 - Alpha
Classifier: Intended Audience :: Developers
Classifier: Operating System :: MacOS
Classifier: Operating System :: POSIX
Classifier: Programming Language :: Python
Classifier: Programming Language :: Python :: 2.6
Classifier: Programming Language :: Python :: 2.7
Classifier: Programming Language :: Python :: 3.4
Classifier: Programming Language :: Python :: 3.6
Classifier: Programming Language :: Python :: 3.7
Classifier: Topic :: Software Development
Classifier: Topic :: Utilities
